nbis/__init__.py
nbis/nbis.py
nbis/uniffi_nbis.dll
nbis_py-0.1.3.dist-info/METADATA
nbis_py-0.1.3.dist-info/WHEEL
nbis_py-0.1.3.dist-info/licenses/LICENSE
nbis_py-0.1.3.dist-info/RECORD
