Metadata-Version: 2.4
Name: nbis-py
Version: 0.1.3
Classifier: Programming Language :: Python :: 3
Classifier: Programming Language :: Rust
Classifier: License :: OSI Approved :: MIT License
Classifier: Operating System :: OS Independent
Summary: Python bindings for NBIS fingerprint processing using Rust + UniFFI
Keywords: fingerprint,nbis,biometrics,rust,uniffi
Home-Page: https://github.com/Seventh-Sense-Artificial-Intelligence/nbis-rs
Author-email: Varun Chatterji <varun@seventhsense.ai>
Requires-Python: >=3.8
Project-URL: Homepage, https://github.com/Seventh-Sense-Artificial-Intelligence/nbis-rs
Project-URL: Repository, https://github.com/Seventh-Sense-Artificial-Intelligence/nbis-rs
